{
    "users": [
        {
            "id": 1,
            "name": "user"
        }
    ],
    "potins": [
        {
            "id": 1,
            "image": "image",
            "name": "name",
            "email": "email",
            "whatshapp": "111111111",
            "latitude": "2222222222",
            "longitude": "3333333333",
            "city": "city",
            "uf": "uf"
        }
    ],
    "item": {
        "id": 1,
        "title": "title",
        "image": "image"
    },
    "pointItems": [
        {
            "porintId": 1,
            "itemId": 1
        }
    ]
}